{
  "backend": {
    "backend": "pylians",
    "mask": {
      "backend": "pylians",
      "backend_metadata": {
        "backend": "pylians",
        "filter_type": "Top-Hat",
        "mas": "CIC",
        "threads": 1
      },
      "diagnostics": {
        "bytes_per_grid": 1048576000,
        "cell_size": 117.1875,
        "cell_volume": 1609325.4089355469,
        "grid_cells": 262144000,
        "grid_dtype": "float32",
        "grid_mass": 558335.6854154383,
        "grid_shape": [
          640,
          640,
          640
        ],
        "groups": [
          {
            "assignment_seconds": 0.5276853367686272,
            "count": 778,
            "filter_seconds": 4.625050812959671,
            "group_id": 0,
            "radius": 0.3472912907600403,
            "radius_grid_cells": 0.0029635523478190105,
            "smooth_seconds": 6.917762313038111,
            "total_seconds": 13.02081161737442
          },
          {
            "assignment_seconds": 0.5647742636501789,
            "count": 22945,
            "filter_seconds": 4.272175543010235,
            "group_id": 1,
            "radius": 0.695351243019104,
            "radius_grid_cells": 0.005933663940429688,
            "smooth_seconds": 8.322523329406977,
            "total_seconds": 13.679745834320784
          },
          {
            "assignment_seconds": 0.560096986591816,
            "count": 146978,
            "filter_seconds": 4.696918901056051,
            "group_id": 2,
            "radius": 1.4443464279174805,
            "radius_grid_cells": 0.012325089518229167,
            "smooth_seconds": 7.064971145242453,
            "total_seconds": 13.069053538143635
          },
          {
            "assignment_seconds": 0.5809912383556366,
            "count": 684060,
            "filter_seconds": 3.8072764091193676,
            "group_id": 3,
            "radius": 3.0122079849243164,
            "radius_grid_cells": 0.0257041748046875,
            "smooth_seconds": 6.889071322977543,
            "total_seconds": 11.919441875070333
          },
          {
            "assignment_seconds": 0.5920809656381607,
            "count": 3404719,
            "filter_seconds": 4.252389006316662,
            "group_id": 4,
            "radius": 6.726558685302734,
            "radius_grid_cells": 0.057399967447916665,
            "smooth_seconds": 6.934997372329235,
            "total_seconds": 12.421908091753721
          },
          {
            "assignment_seconds": 0.8772599995136261,
            "count": 12345295,
            "filter_seconds": 4.1519004590809345,
            "group_id": 5,
            "radius": 13.61860179901123,
            "radius_grid_cells": 0.11621206868489584,
            "smooth_seconds": 6.719305831938982,
            "total_seconds": 13.200208626687527
          },
          {
            "assignment_seconds": 1.8670957870781422,
            "count": 24448609,
            "filter_seconds": 4.138056721538305,
            "group_id": 6,
            "radius": 28.333471298217773,
            "radius_grid_cells": 0.241778955078125,
            "smooth_seconds": 6.676674798130989,
            "total_seconds": 14.483465272933245
          },
          {
            "assignment_seconds": 2.3389051482081413,
            "count": 26021010,
            "filter_seconds": 4.187522992491722,
            "group_id": 7,
            "radius": 56.08342361450195,
            "radius_grid_cells": 0.47857854817708334,
            "smooth_seconds": 6.679659221321344,
            "total_seconds": 15.033604945987463
          },
          {
            "assignment_seconds": 1.739153515547514,
            "count": 17068121,
            "filter_seconds": 3.390498671680689,
            "group_id": 8,
            "radius": 121.32685852050781,
            "radius_grid_cells": 1.0353225260416667,
            "smooth_seconds": 5.802569884806871,
            "total_seconds": 12.279644027352333
          },
          {
            "assignment_seconds": 1.033023327589035,
            "count": 4811071,
            "filter_seconds": 3.5458075292408466,
            "group_id": 9,
            "radius": 214.8326416015625,
            "radius_grid_cells": 1.8332385416666668,
            "smooth_seconds": 6.361456952989101,
            "total_seconds": 11.884533274918795
          }
        ],
        "input_mass": 558335.6681648606,
        "radius_binning": "geometric",
        "radius_bins_requested": 10,
        "radius_bins_used": 10,
        "radius_max": 399.3378601074219,
        "radius_min": 0.18088053166866302,
        "relative_mass_error": 3.089642784788185e-08
      },
      "estimated_full_load_gb": 3.645157240331173,
      "load_mode": "full",
      "particle_metadata": {
        "dropped_count": 0,
        "gas_radius_definition": "sphere radius from cell volume",
        "gas_radius_mode": "sphere",
        "input_count": 88953586,
        "valid_count": 88953586
      },
      "particle_type": "gas",
      "radius_mode": "sphere"
    },
    "target": {
      "backend": "pylians",
      "backend_metadata": {
        "backend": "pylians",
        "filter_type": "Top-Hat",
        "mas": "CIC",
        "threads": 1
      },
      "diagnostics": {
        "bytes_per_grid": 1048576000,
        "cell_size": 117.1875,
        "cell_volume": 1609325.4089355469,
        "grid_cells": 262144000,
        "grid_dtype": "float32",
        "grid_mass": 558335.6854154383,
        "grid_shape": [
          640,
          640,
          640
        ],
        "groups": [
          {
            "assignment_seconds": 0.5276853367686272,
            "count": 778,
            "filter_seconds": 4.625050812959671,
            "group_id": 0,
            "radius": 0.3472912907600403,
            "radius_grid_cells": 0.0029635523478190105,
            "smooth_seconds": 6.917762313038111,
            "total_seconds": 13.02081161737442
          },
          {
            "assignment_seconds": 0.5647742636501789,
            "count": 22945,
            "filter_seconds": 4.272175543010235,
            "group_id": 1,
            "radius": 0.695351243019104,
            "radius_grid_cells": 0.005933663940429688,
            "smooth_seconds": 8.322523329406977,
            "total_seconds": 13.679745834320784
          },
          {
            "assignment_seconds": 0.560096986591816,
            "count": 146978,
            "filter_seconds": 4.696918901056051,
            "group_id": 2,
            "radius": 1.4443464279174805,
            "radius_grid_cells": 0.012325089518229167,
            "smooth_seconds": 7.064971145242453,
            "total_seconds": 13.069053538143635
          },
          {
            "assignment_seconds": 0.5809912383556366,
            "count": 684060,
            "filter_seconds": 3.8072764091193676,
            "group_id": 3,
            "radius": 3.0122079849243164,
            "radius_grid_cells": 0.0257041748046875,
            "smooth_seconds": 6.889071322977543,
            "total_seconds": 11.919441875070333
          },
          {
            "assignment_seconds": 0.5920809656381607,
            "count": 3404719,
            "filter_seconds": 4.252389006316662,
            "group_id": 4,
            "radius": 6.726558685302734,
            "radius_grid_cells": 0.057399967447916665,
            "smooth_seconds": 6.934997372329235,
            "total_seconds": 12.421908091753721
          },
          {
            "assignment_seconds": 0.8772599995136261,
            "count": 12345295,
            "filter_seconds": 4.1519004590809345,
            "group_id": 5,
            "radius": 13.61860179901123,
            "radius_grid_cells": 0.11621206868489584,
            "smooth_seconds": 6.719305831938982,
            "total_seconds": 13.200208626687527
          },
          {
            "assignment_seconds": 1.8670957870781422,
            "count": 24448609,
            "filter_seconds": 4.138056721538305,
            "group_id": 6,
            "radius": 28.333471298217773,
            "radius_grid_cells": 0.241778955078125,
            "smooth_seconds": 6.676674798130989,
            "total_seconds": 14.483465272933245
          },
          {
            "assignment_seconds": 2.3389051482081413,
            "count": 26021010,
            "filter_seconds": 4.187522992491722,
            "group_id": 7,
            "radius": 56.08342361450195,
            "radius_grid_cells": 0.47857854817708334,
            "smooth_seconds": 6.679659221321344,
            "total_seconds": 15.033604945987463
          },
          {
            "assignment_seconds": 1.739153515547514,
            "count": 17068121,
            "filter_seconds": 3.390498671680689,
            "group_id": 8,
            "radius": 121.32685852050781,
            "radius_grid_cells": 1.0353225260416667,
            "smooth_seconds": 5.802569884806871,
            "total_seconds": 12.279644027352333
          },
          {
            "assignment_seconds": 1.033023327589035,
            "count": 4811071,
            "filter_seconds": 3.5458075292408466,
            "group_id": 9,
            "radius": 214.8326416015625,
            "radius_grid_cells": 1.8332385416666668,
            "smooth_seconds": 6.361456952989101,
            "total_seconds": 11.884533274918795
          }
        ],
        "input_mass": 558335.6681648606,
        "radius_binning": "geometric",
        "radius_bins_requested": 10,
        "radius_bins_used": 10,
        "radius_max": 399.3378601074219,
        "radius_min": 0.18088053166866302,
        "relative_mass_error": 3.089642784788185e-08
      },
      "estimated_full_load_gb": 3.645157240331173,
      "load_mode": "full",
      "particle_metadata": {
        "dropped_count": 0,
        "gas_radius_definition": "sphere radius from cell volume",
        "gas_radius_mode": "sphere",
        "input_count": 88953586,
        "valid_count": 88953586
      },
      "particle_type": "gas",
      "radius_mode": "sphere"
    }
  },
  "clumping_factors": [
    null,
    1.354159242188698,
    1.4132664795107521,
    1.5758091031241868,
    1.7241382564215697,
    1.8447286839945016,
    1.9533311894162577,
    2.054223634927506,
    2.1482229375352135,
    2.234641415596451,
    2.312913482347827,
    2.383445197980416,
    2.4476819570815236,
    2.507622415421048,
    2.565484575882674,
    2.623534706251091,
    2.68273436272759,
    2.744238952649191,
    2.8082992541226197,
    2.875176206046531,
    2.9447961119152612,
    3.0169402999222843,
    3.0912866964996333,
    3.1673216791298,
    3.244978706467991,
    3.323632159274232,
    3.403164616921936,
    3.4828547989738623,
    3.562780228128963,
    3.6427900269892497,
    3.722244249256358,
    3.801243850248812,
    3.8795312822193293,
    3.957236723198657,
    4.034233308807624,
    4.11026841667133,
    4.185084271972144,
    4.259166220591851,
    4.332353280589064,
    4.404534034718208,
    4.475649916395376,
    4.545811070482684,
    4.614768585787832,
    4.6827226177674515,
    4.749612467143812,
    4.815503131421709,
    4.88071570392448,
    4.94485005303787,
    5.008056785825364,
    5.070517041428394,
    5.132224915757132,
    5.1929543517655015,
    5.253194684334636,
    5.312243774775633,
    5.371028143094774,
    5.428834596828282,
    5.486132039590812,
    5.542763074976362,
    5.59856577358334,
    5.654087411597237,
    5.70874310599216,
    5.76279178597822,
    5.816381410838676,
    5.869365886428169,
    5.921940059426948,
    5.9735605445155056,
    6.025237318724436,
    6.075760966449463,
    6.1263256885485715,
    6.176231195114581,
    6.225985636008113,
    6.2752614051652875,
    6.324128285151033,
    6.372398222021743,
    6.420057048968658,
    6.467691567129845,
    6.515015730020893,
    6.56187983914375,
    6.608415218323221,
    6.654414722657972,
    6.700075613939613,
    6.745837998906662,
    6.790572727412556,
    6.835482966914118,
    6.880344546010325,
    6.924454891625289,
    6.96838866232449,
    7.011697163753621,
    7.054985623590877,
    7.097842118477536,
    7.139816745623323,
    7.18190558088757,
    7.224296642917841,
    7.26624848830295,
    7.307797862472662,
    7.349520040102051,
    7.390958149826562,
    7.431925163737298,
    7.4726449544760625,
    7.512677326972285,
    7.5524390800287575,
    7.5925508996212345,
    7.6322359657865055,
    7.671908579378674,
    7.710897666305989,
    7.749784536453056,
    7.788428740061074,
    7.826692050782448,
    7.865218068149757,
    7.903120472057344,
    7.941092505269922,
    7.979491537909546,
    8.016961496508388,
    8.054645608071421,
    8.091806432166097,
    8.12903190193781,
    8.165860508154584,
    8.202311180530433,
    8.238634245480354,
    8.275024179588435,
    8.311445805659714,
    8.347605912103344,
    8.383304785508205,
    8.418957442434989,
    8.454428745635125,
    8.489797432325323,
    8.525120648679657,
    8.560141954547213,
    8.594864997350701,
    8.630341938238518,
    8.665038345905964,
    8.699783043606544,
    8.733729559091879,
    8.767760555742326,
    8.80166150860667,
    8.835428181791848,
    8.869393619990225,
    8.903382078714472,
    8.936792381444764,
    8.970349969760024,
    9.00364232674338,
    9.036804977757468,
    9.070414424967467,
    9.103589671325373,
    9.13641341047645,
    9.16872975627926,
    9.201267038013938,
    9.233948687533896,
    9.26614902342801,
    9.29822848426932,
    9.330425124239602,
    9.362803656432693,
    9.394363137518132,
    9.426298290481377,
    9.457771767598624,
    9.48929750012448,
    9.521136670789343,
    9.552911832433528,
    9.584097247460631,
    9.615564159341998,
    9.646546301727453,
    9.677072465662107,
    9.708095966839005,
    9.738600174177488,
    9.76906796086106,
    9.800065084296913,
    9.83104539074073,
    9.861818701272089,
    9.89247798505327,
    9.922724100925839,
    9.952882192296242,
    9.982856655876954,
    10.01284904579277,
    10.042316469665058,
    10.072880755670848,
    10.102287309004547,
    10.131823981261935,
    10.161324849547606,
    10.19039877217423,
    10.219505398928504,
    10.248535612933694,
    10.277769053580613,
    10.306822309591304,
    10.335618644367582,
    10.364473006232352,
    10.393607103699935,
    10.422258112741641,
    10.450976367241385,
    10.479743849497753,
    10.508098135167437,
    10.537279022038994,
    10.565950610062425,
    10.594153159081579,
    10.62258966713609,
    10.650614792280257,
    10.679067026204997,
    10.707203658329886,
    10.735641807357089,
    10.763540423442587,
    10.791594030804518
  ],
  "diagnostics": {
    "clumping": {
      "clumping_definition": "mean(target_density**2 inside mask) / mean(target_density inside mask)**2",
      "mask_mean_density": 1.3234623933146928e-09,
      "overdensity_definition": "mask_density / mean(mask_density) - 1",
      "selected_cell_counts": [
        4372706,
        130527505,
        178545538,
        198693982,
        212811623,
        221766690,
        228040321,
        232707746,
        236274608,
        238995526,
        241046609,
        242583981,
        243751161,
        244664906,
        245413073,
        246058442,
        246632523,
        247160170,
        247652354,
        248117965,
        248561643,
        248986286,
        249393539,
        249783783,
        250159330,
        250519520,
        250865955,
        251197284,
        251515446,
        251821251,
        252113523,
        252393717,
        252661904,
        252919393,
        253166551,
        253403232,
        253629269,
        253846683,
        254055527,
        254255936,
        254448161,
        254632912,
        254809867,
        254979852,
        255143022,
        255299824,
        255451274,
        255596677,
        255736610,
        255871676,
        256002066,
        256127471,
        256249077,
        256365640,
        256479136,
        256588324,
        256694226,
        256796667,
        256895495,
        256991777,
        257084614,
        257174530,
        257261879,
        257346507,
        257428814,
        257508025,
        257585759,
        257660287,
        257733433,
        257804258,
        257873536,
        257940868,
        258006414,
        258069965,
        258131560,
        258192013,
        258250996,
        258308370,
        258364345,
        258418711,
        258471732,
        258523965,
        258574159,
        258623689,
        258672345,
        258719396,
        258765486,
        258810172,
        258854112,
        258896908,
        258938144,
        258978826,
        259019151,
        259058440,
        259096745,
        259134616,
        259171660,
        259207725,
        259243034,
        259277225,
        259310673,
        259343914,
        259376323,
        259408247,
        259439167,
        259469559,
        259499325,
        259528376,
        259557212,
        259585182,
        259612813,
        259640367,
        259666889,
        259693199,
        259718791,
        259744081,
        259768768,
        259792875,
        259816576,
        259840009,
        259863157,
        259885841,
        259907947,
        259929739,
        259951143,
        259972214,
        259992992,
        260013336,
        260033254,
        260053355,
        260072773,
        260091981,
        260110519,
        260128876,
        260146942,
        260164719,
        260182389,
        260199864,
        260216840,
        260233690,
        260250215,
        260266486,
        260282787,
        260298695,
        260314256,
        260329403,
        260344482,
        260359459,
        260374051,
        260388426,
        260402695,
        260416890,
        260430574,
        260444272,
        260457626,
        260470857,
        260484079,
        260497136,
        260509816,
        260522477,
        260534813,
        260546840,
        260558936,
        260570708,
        260582344,
        260594064,
        260605659,
        260617063,
        260628310,
        260639296,
        260650141,
        260660813,
        260671387,
        260681674,
        260692241,
        260702309,
        260712324,
        260722231,
        260731901,
        260741489,
        260750962,
        260760410,
        260769712,
        260778845,
        260787911,
        260796981,
        260805819,
        260814596,
        260823308,
        260831817,
        260840496,
        260848947,
        260857186,
        260865419,
        260873460,
        260881552,
        260889484,
        260897431,
        260905160,
        260912865
      ],
      "selected_cell_fractions": [
        0.016680549621582032,
        0.49792291641235353,
        0.6810971755981445,
        0.7579573898315429,
        0.8118119163513183,
        0.845972785949707,
        0.8699047889709473,
        0.8877096023559571,
        0.9013161010742188,
        0.9116955795288086,
        0.9195198402404785,
        0.925384449005127,
        0.9298368873596191,
        0.9333225479125976,
        0.9361765785217285,
        0.9386384658813477,
        0.9408284111022949,
        0.9428412246704102,
        0.9447187576293945,
        0.9464949226379394,
        0.9481874198913575,
        0.9498073043823242,
        0.9513608512878418,
        0.9528495140075683,
        0.954282112121582,
        0.9556561279296875,
        0.9569776725769042,
        0.9582415924072266,
        0.9594552841186523,
        0.9606218376159668,
        0.9617367668151855,
        0.9628056221008301,
        0.9638286743164063,
        0.9648109169006348,
        0.9657537498474121,
        0.9666566162109375,
        0.9675188789367676,
        0.9683482475280761,
        0.9691449241638184,
        0.969909423828125,
        0.9706427040100097,
        0.9713474731445313,
        0.9720225028991699,
        0.9726709442138672,
        0.9732933883666992,
        0.9738915405273437,
        0.9744692764282227,
        0.9750239448547363,
        0.975557746887207,
        0.976072982788086,
        0.9765703811645507,
        0.9770487632751464,
        0.97751265335083,
        0.9779573059082032,
        0.9783902587890625,
        0.9788067779541015,
        0.9792107620239258,
        0.9796015434265136,
        0.9799785423278808,
        0.9803458290100098,
        0.9806999740600586,
        0.9810429763793945,
        0.9813761863708496,
        0.981699016571045,
        0.9820129928588868,
        0.9823151588439941,
        0.9826116905212402,
        0.9828959922790528,
        0.9831750221252441,
        0.983445198059082,
        0.98370947265625,
        0.983966323852539,
        0.9842163619995117,
        0.9844587898254394,
        0.9846937561035156,
        0.9849243659973145,
        0.9851493682861329,
        0.9853682327270508,
        0.9855817604064941,
        0.9857891502380371,
        0.9859914093017578,
        0.9861906623840332,
        0.986382137298584,
        0.9865710792541504,
        0.9867566871643066,
        0.9869361724853516,
        0.9871119918823242,
        0.9872824554443359,
        0.9874500732421875,
        0.9876133270263672,
        0.9877706298828125,
        0.9879258193969727,
        0.988079647064209,
        0.9882295227050781,
        0.9883756446838379,
        0.9885201110839844,
        0.9886614227294922,
        0.988798999786377,
        0.988933692932129,
        0.9890641212463379,
        0.9891917152404786,
        0.9893185195922851,
        0.9894421501159668,
        0.9895639305114746,
        0.9896818809509277,
        0.9897978172302246,
        0.9899113655090332,
        0.9900221862792968,
        0.9901321868896484,
        0.990238883972168,
        0.9903442878723144,
        0.9904493980407715,
        0.9905505714416504,
        0.990650936126709,
        0.9907485618591308,
        0.9908450355529785,
        0.990939208984375,
        0.9910311698913574,
        0.99112158203125,
        0.9912109718322754,
        0.9912992744445801,
        0.9913858070373535,
        0.9914701347351074,
        0.9915532646179199,
        0.9916349143981934,
        0.9917152938842774,
        0.9917945556640625,
        0.9918721618652344,
        0.991948143005371,
        0.9920248222351075,
        0.9920988960266113,
        0.9921721687316895,
        0.9922428855895996,
        0.9923129119873046,
        0.9923818283081055,
        0.9924496421813965,
        0.9925170478820801,
        0.9925837097167969,
        0.9926484680175781,
        0.9927127456665039,
        0.9927757835388183,
        0.9928378524780274,
        0.9929000358581543,
        0.9929607200622559,
        0.9930200805664062,
        0.9930778617858886,
        0.993135383605957,
        0.9931925163269043,
        0.9932481803894043,
        0.9933030166625977,
        0.9933574485778809,
        0.9934115982055665,
        0.9934637985229492,
        0.9935160522460937,
        0.9935669937133789,
        0.9936174659729003,
        0.9936679039001465,
        0.9937177124023437,
        0.9937660827636718,
        0.993814380645752,
        0.9938614387512207,
        0.9939073181152344,
        0.9939534606933593,
        0.9939983673095704,
        0.9940427551269532,
        0.9940874633789063,
        0.9941316947937012,
        0.9941751976013183,
        0.9942181015014648,
        0.994260009765625,
        0.9943013801574707,
        0.9943420906066894,
        0.9943824272155761,
        0.9944216690063477,
        0.9944619789123536,
        0.9945003852844239,
        0.994538589477539,
        0.9945763816833496,
        0.9946132698059083,
        0.994649845123291,
        0.9946859817504883,
        0.9947220230102539,
        0.9947575073242187,
        0.9947923469543457,
        0.9948269309997558,
        0.9948615303039551,
        0.9948952445983886,
        0.994928726196289,
        0.9949619598388671,
        0.9949944190979004,
        0.9950275268554688,
        0.9950597648620605,
        0.995091194152832,
        0.9951226005554199,
        0.9951532745361328,
        0.9951841430664062,
        0.9952144012451172,
        0.9952447166442872,
        0.9952742004394531,
        0.9953035926818847
      ],
      "selected_density_fractions": [
        -3.131492182158054e-08,
        0.03378547077522828,
        0.06640958723920766,
        0.09133573078413232,
        0.11567232837451351,
        0.1356095928033605,
        0.15272437248101187,
        0.16779161746283777,
        0.18108472713651744,
        0.19258085802208294,
        0.20226795448810062,
        0.2102953437074082,
        0.21697247221943067,
        0.22265680873634572,
        0.22768533102105049,
        0.2323457785293677,
        0.2367784073224646,
        0.24111567119265753,
        0.2454073900637914,
        0.24969957317178895,
        0.25401082404719794,
        0.25834871650188757,
        0.2627120631970455,
        0.2670875677223157,
        0.27148554805474184,
        0.27588329421413493,
        0.2802856345769158,
        0.28466117699838916,
        0.2890214321493431,
        0.29336478310751957,
        0.29766151742956387,
        0.30192035519043586,
        0.3061303347357549,
        0.3103007178788605,
        0.314426902865241,
        0.3184962192733536,
        0.322495186365531,
        0.3264499977676272,
        0.33035296393940894,
        0.3341981795223304,
        0.33798221438433296,
        0.3417110749314159,
        0.3453707641531269,
        0.3489710837346527,
        0.3525084096241584,
        0.3559857987262459,
        0.3594199922107762,
        0.3627895905450983,
        0.36610214582526746,
        0.3693668329890755,
        0.3725834504096908,
        0.37573966454088176,
        0.37886091570465263,
        0.38191077119055866,
        0.3849369241659896,
        0.38790264998377655,
        0.39083190557560016,
        0.39371656392157955,
        0.3965486391276128,
        0.3993557551943408,
        0.40210862829106386,
        0.4048197786149797,
        0.40749702529154086,
        0.4101330617207931,
        0.41273779729473725,
        0.4152840709341444,
        0.4178217165184255,
        0.42029179211761436,
        0.42275254461760664,
        0.4251704357627412,
        0.4275700551887597,
        0.4299358489823411,
        0.43227149526341707,
        0.43456778794012085,
        0.43682412925022357,
        0.43906871431307987,
        0.4412881645464789,
        0.4434756837761953,
        0.4456377086388485,
        0.44776465850170766,
        0.4498655017001066,
        0.45196111120120513,
        0.45399988006130476,
        0.45603644266480137,
        0.45806128575111554,
        0.4600427690833042,
        0.46200674794896085,
        0.4639331989782142,
        0.46584934903048947,
        0.4677369784467218,
        0.4695763507453374,
        0.47141127041310266,
        0.4732502109823312,
        0.4750614325975312,
        0.47684641154373913,
        0.478630070258764,
        0.48039321901656074,
        0.48212780530428884,
        0.483843603440252,
        0.48552210136581947,
        0.4871808000979792,
        0.48884581164045277,
        0.49048524374341107,
        0.49211610296081504,
        0.4937110617085664,
        0.49529393417380274,
        0.4968590744339188,
        0.49840109033685975,
        0.4999460670022383,
        0.5014585890028291,
        0.502966515742873,
        0.5044840390542796,
        0.5059579049229388,
        0.5074330939145434,
        0.5088807997427376,
        0.5103240426448756,
        0.5117451482214501,
        0.5131448741191945,
        0.5145328641842775,
        0.5159168074531919,
        0.5172954510735981,
        0.5186577762369025,
        0.5199963911905564,
        0.52132687327347,
        0.5226443336146213,
        0.5239517987873107,
        0.5252514552212778,
        0.5265340708933598,
        0.5277997656524258,
        0.5290870889742411,
        0.5303403741136702,
        0.5315896791512165,
        0.5328046437104248,
        0.5340169047563593,
        0.5352189487814651,
        0.536410649770554,
        0.5376039625803456,
        0.538792800169987,
        0.539956157969562,
        0.5411193132898005,
        0.5422682231736936,
        0.5434075687751388,
        0.5445571652987148,
        0.5456869876058917,
        0.5467999261875696,
        0.5478907923644684,
        0.5489842580549377,
        0.5500777926404459,
        0.5511505027327026,
        0.5522144453394611,
        0.5532776467709952,
        0.5543423750134322,
        0.5553756300635874,
        0.5564167357069403,
        0.5574383641524842,
        0.5584572125764039,
        0.5594819273092622,
        0.5605003623487087,
        0.5614957150092136,
        0.5624958774355409,
        0.5634765208252819,
        0.5644386046608333,
        0.5654122423362191,
        0.5663656441505377,
        0.5673138564236633,
        0.5682747024502338,
        0.5692311194805946,
        0.5701774340488694,
        0.571116380011234,
        0.572038993862524,
        0.5729551830222536,
        0.5738620894811535,
        0.5747659215471781,
        0.5756503446277542,
        0.5765640957566274,
        0.577439741459472,
        0.5783157580424966,
        0.5791872591051591,
        0.5800427290679983,
        0.58089572751117,
        0.5817431803915432,
        0.5825931433909127,
        0.5834346004250253,
        0.5842653340130008,
        0.5850944936556561,
        0.5859285230050447,
        0.5867456130899753,
        0.5875614519749617,
        0.5883755912528547,
        0.5891749957819425,
        0.5899946784224849,
        0.5907970631913578,
        0.591583406877497,
        0.5923732908030278,
        0.5931487894932834,
        0.5939332247578433,
        0.5947061092499455,
        0.5954844240800445,
        0.5962452272815426,
        0.5970074948239986
      ],
      "selected_density_sums": [
        -1.0864327755157016e-08,
        0.011721454390200763,
        0.023039991157002653,
        0.03168781070728262,
        0.040131094524937086,
        0.047048083701226664,
        0.05298584643730238,
        0.058213242142853575,
        0.06282512337963116,
        0.06681356488264951,
        0.07017438409855799,
        0.07295938825707611,
        0.07527593603679701,
        0.07724804681970861,
        0.07899263090445936,
        0.08060951596342732,
        0.08214736211548009,
        0.08365212257807537,
        0.08514108176228315,
        0.08663020200777256,
        0.0881259375811206,
        0.08963091612339154,
        0.09114472570195827,
        0.09266275329045277,
        0.09418857858436376,
        0.09571432263481523,
        0.09724166058774115,
        0.09875970132385821,
        0.1002724383291101,
        0.10177931063216612,
        0.10327000986550579,
        0.10474756135210302,
        0.10620816208051782,
        0.10765502532320544,
        0.10908655455792167,
        0.11049835393743364,
        0.11188574648527523,
        0.11325781975842626,
        0.1146119059652871,
        0.11594595631419476,
        0.11725878076293424,
        0.11855246316034214,
        0.11982214741544646,
        0.12107123410261329,
        0.12229846590154143,
        0.12350490336776095,
        0.12469635464466784,
        0.1258653954270746,
        0.12701464582201033,
        0.12814728896152544,
        0.12926325489366547,
        0.13035826464595185,
        0.13144114442584015,
        0.13249925435162996,
        0.13354914098234377,
        0.1345780631524181,
        0.13559433242524338,
        0.13659512923102596,
        0.13757768296182898,
        0.1385515774256077,
        0.1395066529567413,
        0.14044725328397006,
        0.14137609115689492,
        0.14229063164034567,
        0.14319431267624544,
        0.14407771106154083,
        0.14495811604901415,
        0.1458150784595385,
        0.14666880633523177,
        0.14750766398995313,
        0.14834018249600095,
        0.14916096561406295,
        0.14997128942270282,
        0.15076795998134634,
        0.15155076990372535,
        0.1523295011404227,
        0.15309951215655399,
        0.15385844510289043,
        0.15460853309150152,
        0.15534645223945748,
        0.15607531400062175,
        0.15680235999474795,
        0.15750968582616248,
        0.158216246223929,
        0.1589187406790587,
        0.1596061919997081,
        0.16028757036055047,
        0.16095592889918314,
        0.16162071364029124,
        0.16227560349679698,
        0.16291375113867118,
        0.16355035399492507,
        0.16418835185358766,
        0.1648167329613826,
        0.16543600949728293,
        0.1660548279951793,
        0.16666653081516208,
        0.16726832423674082,
        0.16786359933967737,
        0.16844593359245358,
        0.16902139875809957,
        0.16959905407579817,
        0.1701678349209284,
        0.1707336415086423,
        0.17128699286906574,
        0.17183615104212208,
        0.1723791572442635,
        0.17291414073451988,
        0.1734501514249625,
        0.17397490236781749,
        0.17449805904142962,
        0.17502454512768423,
        0.17553588480004506,
        0.17604768351367134,
        0.1765499472810908,
        0.17705066269109465,
        0.1775436978277159,
        0.1780293155471891,
        0.17851086166357027,
        0.17899100379369265,
        0.17946930727581495,
        0.1799419492695445,
        0.1804063652970636,
        0.18086795972490527,
        0.18132503641927605,
        0.1817786454126334,
        0.18222954525993834,
        0.18267453302407183,
        0.18311365028512788,
        0.1835602713105529,
        0.18399508320639618,
        0.18442851425474444,
        0.18485003129564098,
        0.18527061038579112,
        0.18568764480597216,
        0.18610109083676135,
        0.18651509606895927,
        0.18692754867845657,
        0.18733116138753864,
        0.18773470384890018,
        0.18813330403097545,
        0.18852858600265093,
        0.18892742440593607,
        0.18931940238755757,
        0.18970552276785418,
        0.1900839853982375,
        0.19046334989794672,
        0.19084273829994408,
        0.19121490189961526,
        0.1915840237278082,
        0.19195288841435448,
        0.19232228280920288,
        0.19268075796630263,
        0.19304195679035124,
        0.1933963982396903,
        0.19374987519464987,
        0.19410538739349043,
        0.19445872092978106,
        0.19480404631801945,
        0.1951510403954731,
        0.195491262582767,
        0.19582504576054155,
        0.19616283740123058,
        0.1964936084583047,
        0.1968225790677603,
        0.19715593280290228,
        0.1974877499521724,
        0.1978160621762231,
        0.19814181795289826,
        0.19846190750410236,
        0.19877976808742864,
        0.1990944081516413,
        0.19940798159298218,
        0.19971482132505464,
        0.20003183606350056,
        0.20033563059210585,
        0.20063955379303727,
        0.20094191038960424,
        0.20123870519285908,
        0.20153464253270165,
        0.20182865590759952,
        0.20212354013747308,
        0.20241547332710602,
        0.2027036861487253,
        0.20299135290933484,
        0.20328070915492297,
        0.20356418853062613,
        0.20384723381786635,
        0.2041296894472871,
        0.20440703303646962,
        0.20469141186752032,
        0.2049697894143157,
        0.20524260170435077,
        0.20551664223698857,
        0.2057856919888173,
        0.20605784217541007,
        0.2063259849632771,
        0.20659601174025816,
        0.20685996307264026,
        0.2071244224401439
      ],
      "target_mean_density": 1.3234623933146928e-09,
      "target_total_density_sum": 0.34693772563308684,
      "total_cells": 262144000
    }
  },
  "parameters": {
    "base_path": "../tng100-3/output",
    "grid_size": 640,
    "mask": {
      "backend": "pylians",
      "particle_type": "gas",
      "radius_mode": "sphere"
    },
    "radius_bins": 10,
    "simulation_name": "tng100-3",
    "snapshot": 98,
    "target": {
      "backend": "pylians",
      "particle_type": "gas",
      "radius_mode": "sphere"
    },
    "threshold_count": 200,
    "threshold_max": 25.0,
    "threshold_min": -1.0
  },
  "particle_type": "gas",
  "schema_version": 1,
  "simulation": {
    "base_path": "../tng100-3/output",
    "name": "tng100-3",
    "snapshot": 98
  },
  "thresholds": [
    -1.0,
    -0.8693467336683417,
    -0.7386934673366834,
    -0.6080402010050251,
    -0.4773869346733668,
    -0.3467336683417085,
    -0.2160804020100502,
    -0.08542713567839189,
    0.045226130653266416,
    0.1758793969849246,
    0.306532663316583,
    0.43718592964824143,
    0.5678391959798996,
    0.6984924623115578,
    0.8291457286432162,
    0.9597989949748746,
    1.0904522613065328,
    1.221105527638191,
    1.3517587939698492,
    1.4824120603015079,
    1.613065326633166,
    1.7437185929648242,
    1.8743718592964829,
    2.005025125628141,
    2.1356783919597992,
    2.2663316582914574,
    2.3969849246231156,
    2.5276381909547743,
    2.6582914572864325,
    2.7889447236180906,
    2.9195979899497493,
    3.050251256281407,
    3.1809045226130657,
    3.3115577889447243,
    3.442211055276382,
    3.5728643216080407,
    3.7035175879396984,
    3.834170854271357,
    3.9648241206030157,
    4.0954773869346734,
    4.226130653266332,
    4.356783919597991,
    4.4874371859296485,
    4.618090452261307,
    4.748743718592966,
    4.8793969849246235,
    5.010050251256282,
    5.14070351758794,
    5.2713567839195985,
    5.402010050251257,
    5.532663316582915,
    5.6633165829145735,
    5.793969849246231,
    5.92462311557789,
    6.0552763819095485,
    6.185929648241206,
    6.316582914572865,
    6.4472361809045236,
    6.577889447236181,
    6.70854271356784,
    6.839195979899499,
    6.969849246231156,
    7.100502512562814,
    7.231155778894474,
    7.361809045226131,
    7.492462311557789,
    7.623115577889449,
    7.753768844221106,
    7.884422110552764,
    8.015075376884424,
    8.145728643216081,
    8.27638190954774,
    8.407035175879397,
    8.537688442211056,
    8.668341708542714,
    8.798994974874372,
    8.929648241206031,
    9.06030150753769,
    9.190954773869347,
    9.321608040201006,
    9.452261306532664,
    9.582914572864322,
    9.713567839195981,
    9.84422110552764,
    9.974874371859297,
    10.105527638190956,
    10.236180904522614,
    10.366834170854272,
    10.497487437185931,
    10.62814070351759,
    10.758793969849247,
    10.889447236180905,
    11.020100502512564,
    11.150753768844222,
    11.28140703517588,
    11.41206030150754,
    11.542713567839197,
    11.673366834170855,
    11.804020100502514,
    11.934673366834172,
    12.06532663316583,
    12.19597989949749,
    12.326633165829147,
    12.457286432160805,
    12.587939698492463,
    12.718592964824122,
    12.84924623115578,
    12.979899497487438,
    13.110552763819097,
    13.241206030150755,
    13.371859296482413,
    13.502512562814072,
    13.63316582914573,
    13.763819095477388,
    13.894472361809047,
    14.025125628140705,
    14.155778894472363,
    14.286432160804022,
    14.41708542713568,
    14.547738693467338,
    14.678391959798997,
    14.809045226130655,
    14.939698492462313,
    15.070351758793972,
    15.201005025125628,
    15.331658291457288,
    15.462311557788947,
    15.592964824120603,
    15.723618090452263,
    15.854271356783922,
    15.984924623115578,
    16.115577889447238,
    16.246231155778897,
    16.376884422110553,
    16.507537688442213,
    16.638190954773872,
    16.768844221105528,
    16.899497487437188,
    17.030150753768847,
    17.160804020100503,
    17.291457286432163,
    17.422110552763822,
    17.55276381909548,
    17.683417085427138,
    17.814070351758794,
    17.944723618090453,
    18.075376884422113,
    18.20603015075377,
    18.33668341708543,
    18.467336683417088,
    18.597989949748744,
    18.728643216080403,
    18.859296482412063,
    18.98994974874372,
    19.12060301507538,
    19.251256281407038,
    19.381909547738694,
    19.512562814070353,
    19.643216080402013,
    19.77386934673367,
    19.90452261306533,
    20.035175879396988,
    20.165829145728644,
    20.296482412060303,
    20.427135678391963,
    20.55778894472362,
    20.68844221105528,
    20.819095477386938,
    20.949748743718594,
    21.080402010050253,
    21.211055276381913,
    21.34170854271357,
    21.47236180904523,
    21.603015075376888,
    21.733668341708544,
    21.864321608040203,
    21.994974874371863,
    22.12562814070352,
    22.25628140703518,
    22.386934673366834,
    22.517587939698494,
    22.648241206030153,
    22.77889447236181,
    22.90954773869347,
    23.04020100502513,
    23.170854271356784,
    23.301507537688444,
    23.432160804020103,
    23.56281407035176,
    23.69346733668342,
    23.82412060301508,
    23.954773869346734,
    24.085427135678394,
    24.216080402010054,
    24.34673366834171,
    24.47738693467337,
    24.60804020100503,
    24.738693467336685,
    24.869346733668344,
    25.0
  ],
  "timings": {
    "clumping_cumulative_sums": 4.0907023176550865,
    "clumping_mask_overdensity": 0.4079233221709728,
    "clumping_sort": 41.07513742521405,
    "clumping_threshold_lookup": 1.3279221542179585,
    "target_grid_build_density_grid": 138.15229088813066,
    "target_grid_radius_grouping": 6.83111184835434,
    "target_load_data": 151.89647955447435,
    "total": 356.59901700541377
  }
}